{
  "instance": "r1_2_10",
  "cost": 3376.2409390345097,
  "nv": 18,
  "routes": [
    [
      4,
      188,
      15,
      184,
      166,
      153,
      71,
      193,
      33,
      186,
      144,
      179,
      190,
      167,
      107
    ],
    [
      140,
      196,
      38,
      84,
      114,
      19,
      178,
      23,
      22,
      96,
      29,
      65,
      164
    ],
    [
      57,
      173,
      20,
      98,
      163,
      136,
      95,
      177,
      6,
      189,
      102,
      10,
      97
    ],
    [
      112,
      152,
      30,
      34,
      88,
      99,
      183,
      118,
      32,
      90,
      138,
      45
    ],
    [
      67,
      63,
      44,
      5,
      3,
      117,
      160,
      180,
      195,
      27,
      28,
      91
    ],
    [
      87,
      92,
      48,
      161,
      122,
      8,
      2,
      17,
      76,
      42,
      53,
      192
    ],
    [
      54,
      85,
      94,
      12,
      82,
      47,
      58,
      127,
      77,
      198,
      74,
      108
    ],
    [
      155,
      41,
      7,
      55,
      150,
      137,
      36,
      68,
      116,
      25,
      119
    ],
    [
      157,
      56,
      175,
      9,
      39,
      37,
      110,
      174,
      83,
      52,
      24
    ],
    [
      72,
      147,
      135,
      93,
      199,
      109,
      133,
      64,
      80,
      182,
      75
    ],
    [
      132,
      14,
      18,
      176,
      143,
      1,
      134,
      103,
      124,
      154
    ],
    [
      46,
      89,
      106,
      125,
      151,
      141,
      191,
      43,
      129,
      70
    ],
    [
      120,
      51,
      26,
      123,
      21,
      126,
      156,
      172,
      79,
      197
    ],
    [
      13,
      104,
      100,
      159,
      62,
      194,
      142,
      128,
      40,
      200
    ],
    [
      168,
      139,
      187,
      162,
      115,
      16,
      171,
      170,
      78,
      148
    ],
    [
      81,
      158,
      50,
      66,
      131,
      86,
      11,
      130,
      49,
      61
    ],
    [
      149,
      73,
      60,
      35,
      145,
      121,
      111,
      59,
      105
    ],
    [
      69,
      165,
      31,
      113,
      185,
      169,
      146,
      181,
      101
    ]
  ],
  "algo": "Hybrid-DDQN"
}